CSVD/CSVD.py
CSVD/__init__.py
CSVD/watrem.py
CSVD-0.1.6.dist-info/LICENSE
CSVD-0.1.6.dist-info/METADATA
CSVD-0.1.6.dist-info/WHEEL
CSVD-0.1.6.dist-info/top_level.txt
CSVD-0.1.6.dist-info/RECORD
