Metadata-Version: 2.1
Name: CSVD
Version: 0.1.6
Summary: Fast and Scalable Water Removal in MR Spectroscopic Data using Casorati Lanczos Singular Value Decomposition
Home-page: https://github.com/pypa/sampleproject
Author: amir shamaei
Author-email: amirshamaei@isibrno.cz
Project-URL: Bug Tracker, https://github.com/amirshamaei/CSVD
Classifier: Programming Language :: Python :: 3
Classifier: License :: OSI Approved :: MIT License
Classifier: Operating System :: OS Independent
Requires-Python: >=3.6
License-File: LICENSE
Requires-Dist: hlsvdpro
